src/__init__.py
src/__main__.py
src/config.py
src/enums.py
src/main.py
src/server.py
src/openmetadata/__init__.py
src/openmetadata/bots.py
src/openmetadata/charts.py
src/openmetadata/classifications.py
src/openmetadata/containers.py
src/openmetadata/dashboards.py
src/openmetadata/database.py
src/openmetadata/domains.py
src/openmetadata/events.py
src/openmetadata/glossary.py
src/openmetadata/lineage.py
src/openmetadata/metrics.py
src/openmetadata/mlmodels.py
src/openmetadata/openmetadata_client.py
src/openmetadata/pipelines.py
src/openmetadata/policies.py
src/openmetadata/reports.py
src/openmetadata/roles.py
src/openmetadata/schema.py
src/openmetadata/search.py
src/openmetadata/services.py
src/openmetadata/table.py
src/openmetadata/tags.py
src/openmetadata/teams.py
src/openmetadata/test_cases.py
src/openmetadata/test_suites.py
src/openmetadata/topics.py
src/openmetadata/usage.py
src/openmetadata/users.py
mseep_mcp_server_openmetadata-0.2.7.dist-info/METADATA
mseep_mcp_server_openmetadata-0.2.7.dist-info/WHEEL
mseep_mcp_server_openmetadata-0.2.7.dist-info/entry_points.txt
mseep_mcp_server_openmetadata-0.2.7.dist-info/licenses/LICENSE
mseep_mcp_server_openmetadata-0.2.7.dist-info/RECORD
